pyRecommenderSystem/__init__.py
pyRecommenderSystem/algorithm/__init__.py
pyRecommenderSystem/algorithm/cb_tf_idf.py
pyRecommenderSystem/algorithm/cf_item.py
pyRecommenderSystem/algorithm/cf_lf.py
pyRecommenderSystem/algorithm/cf_nn.py
pyRecommenderSystem/algorithm/cf_svd.py
pyRecommenderSystem/algorithm/cf_user.py
pyRecommenderSystem/algorithm/cf_user_item.py
pyRecommenderSystem/util/__init__.py
pyRecommenderSystem/util/gwo.py
pyRecommenderSystem-1.5.2.dist-info/LICENSE
pyRecommenderSystem-1.5.2.dist-info/METADATA
pyRecommenderSystem-1.5.2.dist-info/WHEEL
pyRecommenderSystem-1.5.2.dist-info/top_level.txt
pyRecommenderSystem-1.5.2.dist-info/zip-safe
pyRecommenderSystem-1.5.2.dist-info/RECORD
