Metadata-Version: 2.1
Name: pyRecommenderSystem
Version: 1.5.2
Summary: A Recommender System Python Library
Home-page: https://github.com/Valdecy/pyRecommenderSystem
Author: Valdecy Pereira
Author-email: valdecy.pereira@gmail.com
License: GNU
Platform: UNKNOWN
License-File: LICENSE
Requires-Dist: numpy
Requires-Dist: pandas
Requires-Dist: plotly
Requires-Dist: matplotlib
Requires-Dist: sklearn
